{
  "type": "function",
  "function": {
    "name": "generate_character_description",
    "description": "craft a detailed and vivid description of the character's appearance suitable for an image-generating AI.",
    "parameters": {
      "type": "object",
      "properties": {
        "description": {
          "type": "string",
          "description": "The detailed and vivid description. Follow the provided instructions. You are prohibited from repeating the provided information verbatim."
        }
      },
      "required": [
        "description"
      ]
    }
  }
}